snap_tam/__init__.py
snap_tam/__main__.py
snap_tam/aggregate_api.py
snap_tam/aggregate_filesystem.py
snap_tam/cli.py
snap_tam/config.json
snap_tam-1.0.8.dist-info/METADATA
snap_tam-1.0.8.dist-info/WHEEL
snap_tam-1.0.8.dist-info/entry_points.txt
snap_tam-1.0.8.dist-info/top_level.txt
snap_tam-1.0.8.dist-info/RECORD
