Metadata-Version: 2.1
Name: snap-tam
Version: 1.0.8
Summary: Utility for ModelTB.org team. Aggregates SNaP reports to a single file.
Home-page: http://www.modeltb.org
Author: Joe Flack
Author-email: jflack@jhu.edu
License: UNKNOWN
Platform: UNKNOWN
Requires-Dist: openpyxl (>=3.0.5)
Requires-Dist: pandas (>=1.1.5)
